flatten_spark_dataframe/__init__.py
flatten_spark_dataframe-0.0.1.dist-info/LICENSE
flatten_spark_dataframe-0.0.1.dist-info/METADATA
flatten_spark_dataframe-0.0.1.dist-info/WHEEL
flatten_spark_dataframe-0.0.1.dist-info/top_level.txt
flatten_spark_dataframe-0.0.1.dist-info/RECORD
