Metadata-Version: 2.1
Name: flatten-spark-dataframe
Version: 0.0.1
Summary: Databricks PySpark module to flatten nested spark dataframes, basically struct and array of struct till the specified level
Home-page: https://github.com/PraveenKumar-21/flatten_spark_dataframe
Author: Praveen Kumar B
Author-email: bpraveenkumar21@gmail.com
License: UNKNOWN
Keywords: PySpark flatten dataframe,Databricks PySpark flatten dataframe,PySpark nested dataframe,databricks pyspark nested dataframe,flatten dataframe,nested dataframe
Platform: UNKNOWN
Classifier: Programming Language :: Python :: 3
Classifier: License :: OSI Approved :: MIT License
Classifier: Operating System :: OS Independent
Requires-Python: >=3.6
License-File: LICENSE
Requires-Dist: pyspark
